README.md
setup.cfg
setup.py
cv3/__init__.py
cv3/_utils.py
cv3/color_spaces.py
cv3/create.py
cv3/draw.py
cv3/io.py
cv3/opt.py
cv3/processing.py
cv3/transform.py
cv3/utils.py
cv3/video.py
cv_3.egg-info/PKG-INFO
cv_3.egg-info/SOURCES.txt
cv_3.egg-info/dependency_links.txt
cv_3.egg-info/requires.txt
cv_3.egg-info/top_level.txt