Metadata-Version: 1.0
Name: cv-3
Version: 1.2.0
Summary: Pythonic cv2
Home-page: https://github.com/gorodion/pycv
Author: gorodion
Author-email: domonion@list.ru
License: Apache 2.0
Platform: UNKNOWN
